{"status":"done","chunks":{"accounts":[{"name":"accounts-6719fcaaa7b6733af1e7.js","path":"D:\\Робота\\Code\\EDMS\\PLXK\\static\\bundles\\accounts-6719fcaaa7b6733af1e7.js"}],"boards":[{"name":"boards-6719fcaaa7b6733af1e7.js","path":"D:\\Робота\\Code\\EDMS\\PLXK\\static\\bundles\\boards-6719fcaaa7b6733af1e7.js"}],"correspondence":[{"name":"correspondence-6719fcaaa7b6733af1e7.js","path":"D:\\Робота\\Code\\EDMS\\PLXK\\static\\bundles\\correspondence-6719fcaaa7b6733af1e7.js"}],"docs":[{"name":"docs-6719fcaaa7b6733af1e7.js","path":"D:\\Робота\\Code\\EDMS\\PLXK\\static\\bundles\\docs-6719fcaaa7b6733af1e7.js"}],"edms":[{"name":"edms-6719fcaaa7b6733af1e7.js","path":"D:\\Робота\\Code\\EDMS\\PLXK\\static\\bundles\\edms-6719fcaaa7b6733af1e7.js"}],"hr":[{"name":"hr-6719fcaaa7b6733af1e7.js","path":"D:\\Робота\\Code\\EDMS\\PLXK\\static\\bundles\\hr-6719fcaaa7b6733af1e7.js"}],"ordering":[{"name":"ordering-6719fcaaa7b6733af1e7.js","path":"D:\\Робота\\Code\\EDMS\\PLXK\\static\\bundles\\ordering-6719fcaaa7b6733af1e7.js"}]}}