{"status":"done","chunks":{"accounts":[{"name":"accounts-b3ee22efa17a99dc72ae.js","path":"C:\\Users\\Stas\\Code\\PLXK\\static\\bundles\\accounts-b3ee22efa17a99dc72ae.js"}],"boards":[{"name":"boards-b3ee22efa17a99dc72ae.js","path":"C:\\Users\\Stas\\Code\\PLXK\\static\\bundles\\boards-b3ee22efa17a99dc72ae.js"}],"contract_reg_numbers":[{"name":"contract_reg_numbers-b3ee22efa17a99dc72ae.js","path":"C:\\Users\\Stas\\Code\\PLXK\\static\\bundles\\contract_reg_numbers-b3ee22efa17a99dc72ae.js"}],"corr_templates":[{"name":"corr_templates-b3ee22efa17a99dc72ae.js","path":"C:\\Users\\Stas\\Code\\PLXK\\static\\bundles\\corr_templates-b3ee22efa17a99dc72ae.js"}],"correspondence":[{"name":"correspondence-b3ee22efa17a99dc72ae.js","path":"C:\\Users\\Stas\\Code\\PLXK\\static\\bundles\\correspondence-b3ee22efa17a99dc72ae.js"}],"counterparties":[{"name":"counterparties-b3ee22efa17a99dc72ae.js","path":"C:\\Users\\Stas\\Code\\PLXK\\static\\bundles\\counterparties-b3ee22efa17a99dc72ae.js"}],"docs":[{"name":"docs-b3ee22efa17a99dc72ae.js","path":"C:\\Users\\Stas\\Code\\PLXK\\static\\bundles\\docs-b3ee22efa17a99dc72ae.js"}],"edms":[{"name":"edms-b3ee22efa17a99dc72ae.js","path":"C:\\Users\\Stas\\Code\\PLXK\\static\\bundles\\edms-b3ee22efa17a99dc72ae.js"}],"foyer":[{"name":"foyer-b3ee22efa17a99dc72ae.js","path":"C:\\Users\\Stas\\Code\\PLXK\\static\\bundles\\foyer-b3ee22efa17a99dc72ae.js"}],"hr":[{"name":"hr-b3ee22efa17a99dc72ae.js","path":"C:\\Users\\Stas\\Code\\PLXK\\static\\bundles\\hr-b3ee22efa17a99dc72ae.js"}],"non_compliances":[{"name":"non_compliances-b3ee22efa17a99dc72ae.js","path":"C:\\Users\\Stas\\Code\\PLXK\\static\\bundles\\non_compliances-b3ee22efa17a99dc72ae.js"}],"ordering":[{"name":"ordering-b3ee22efa17a99dc72ae.js","path":"C:\\Users\\Stas\\Code\\PLXK\\static\\bundles\\ordering-b3ee22efa17a99dc72ae.js"}],"permissions":[{"name":"permissions-b3ee22efa17a99dc72ae.js","path":"C:\\Users\\Stas\\Code\\PLXK\\static\\bundles\\permissions-b3ee22efa17a99dc72ae.js"}],"production":[{"name":"production-b3ee22efa17a99dc72ae.js","path":"C:\\Users\\Stas\\Code\\PLXK\\static\\bundles\\production-b3ee22efa17a99dc72ae.js"}],"reclamations":[{"name":"reclamations-b3ee22efa17a99dc72ae.js","path":"C:\\Users\\Stas\\Code\\PLXK\\static\\bundles\\reclamations-b3ee22efa17a99dc72ae.js"}],"vacations":[{"name":"vacations-b3ee22efa17a99dc72ae.js","path":"C:\\Users\\Stas\\Code\\PLXK\\static\\bundles\\vacations-b3ee22efa17a99dc72ae.js"}]}}