{"status":"done","chunks":{"accounts":[{"name":"accounts-42c141794e5ae4ad2691.js","path":"D:\\Робота\\Code\\EDMS\\PLXK\\static\\bundles\\accounts-42c141794e5ae4ad2691.js"}],"boards":[{"name":"boards-42c141794e5ae4ad2691.js","path":"D:\\Робота\\Code\\EDMS\\PLXK\\static\\bundles\\boards-42c141794e5ae4ad2691.js"}],"correspondence":[{"name":"correspondence-42c141794e5ae4ad2691.js","path":"D:\\Робота\\Code\\EDMS\\PLXK\\static\\bundles\\correspondence-42c141794e5ae4ad2691.js"}],"docs":[{"name":"docs-42c141794e5ae4ad2691.js","path":"D:\\Робота\\Code\\EDMS\\PLXK\\static\\bundles\\docs-42c141794e5ae4ad2691.js"}],"edms":[{"name":"edms-42c141794e5ae4ad2691.js","path":"D:\\Робота\\Code\\EDMS\\PLXK\\static\\bundles\\edms-42c141794e5ae4ad2691.js"}],"hr":[{"name":"hr-42c141794e5ae4ad2691.js","path":"D:\\Робота\\Code\\EDMS\\PLXK\\static\\bundles\\hr-42c141794e5ae4ad2691.js"}],"ordering":[{"name":"ordering-42c141794e5ae4ad2691.js","path":"D:\\Робота\\Code\\EDMS\\PLXK\\static\\bundles\\ordering-42c141794e5ae4ad2691.js"}]}}