{"status":"done","chunks":{"accounts":[{"name":"accounts-028ade3b55d754dd3092.js","path":"D:\\Робота\\Code\\EDMS\\PLXK\\static\\bundles\\accounts-028ade3b55d754dd3092.js"}],"boards":[{"name":"boards-028ade3b55d754dd3092.js","path":"D:\\Робота\\Code\\EDMS\\PLXK\\static\\bundles\\boards-028ade3b55d754dd3092.js"}],"correspondence":[{"name":"correspondence-028ade3b55d754dd3092.js","path":"D:\\Робота\\Code\\EDMS\\PLXK\\static\\bundles\\correspondence-028ade3b55d754dd3092.js"}],"docs":[{"name":"docs-028ade3b55d754dd3092.js","path":"D:\\Робота\\Code\\EDMS\\PLXK\\static\\bundles\\docs-028ade3b55d754dd3092.js"}],"edms":[{"name":"edms-028ade3b55d754dd3092.js","path":"D:\\Робота\\Code\\EDMS\\PLXK\\static\\bundles\\edms-028ade3b55d754dd3092.js"}],"hr":[{"name":"hr-028ade3b55d754dd3092.js","path":"D:\\Робота\\Code\\EDMS\\PLXK\\static\\bundles\\hr-028ade3b55d754dd3092.js"}],"ordering":[{"name":"ordering-028ade3b55d754dd3092.js","path":"D:\\Робота\\Code\\EDMS\\PLXK\\static\\bundles\\ordering-028ade3b55d754dd3092.js"}]}}